{"from":1,"to":12,"nombreRemitente":"Gabriel","idDestinatario":12,"msj":"123344444","fecha":"11-09-2018 22:33:34"}
{"from":1,"to":1,"nombreRemitente":"Gabriel","idDestinatario":1,"msj":"from gabriel to gabriel","fecha":"11-09-2018 22:40:47"}
{"from":1,"to":2,"nombreRemitente":"Gabriel","idDestinatario":2,"msj":"enviado 23:04","fecha":"11-09-2018 23:04:54"}
{"from":2,"to":1,"nombreRemitente":"Joaco","idDestinatario":1,"msj":"enviado 23:05","fecha":"11-09-2018 23:05:54"}
{"from":1,"to":1,"nombreRemitente":"Gabriel","idDestinatario":1,"msj":"de nuevo 01:21\r\n","fecha":"12-09-2018 01:21:52"}
{"from":1,"to":2,"nombreRemitente":"Gabriel","idDestinatario":2,"msj":"prueba a Joaco","fecha":"12-09-2018 01:24:23"}
{"from":1,"to":2,"nombreRemitente":"Gabriel","idDestinatario":2,"msj":"mensaje 3","fecha":"12-09-2018 01:28:20"}
{"from":1,"to":2,"nombreRemitente":"Gabriel","idDestinatario":2,"msj":"mensaje 4","fecha":"12-09-2018 01:28:56"}
{"from":1,"to":1,"nombreRemitente":"Gabriel","idDestinatario":1,"msj":"prueba","fecha":"12-09-2018 01:29:37"}
{"from":1,"to":1,"nombreRemitente":"Gabriel","idDestinatario":1,"msj":"prueba a mi mismo","fecha":"12-09-2018 01:31:39"}
{"from":1,"to":1,"nombreRemitente":"Gabriel","idDestinatario":1,"msj":"mensaje a mi mismo","fecha":"12-09-2018 01:32:28"}
{"from":1,"to":1,"nombreRemitente":"Gabriel","idDestinatario":1,"msj":"123456..","fecha":"12-09-2018 01:37:01"}
{"from":1,"to":1,"nombreRemitente":"Gabriel","idDestinatario":1,"msj":"hhjhjhjhjh","fecha":"12-09-2018 01:41:07"}
{"from":1,"to":1,"nombreRemitente":"Gabriel","idDestinatario":1,"msj":"","fecha":"12-09-2018 01:42:20"}
{"from":1,"to":1,"nombreRemitente":"Gabriel","idDestinatario":1,"msj":"hhhhhhhhhhhh","fecha":"12-09-2018 01:42:37"}
{"from":1,"to":1,"nombreRemitente":"Gabriel","idDestinatario":1,"msj":"hhhhhhhhhhhhhhhh","fecha":"12-09-2018 01:42:57"}
{"from":1,"to":1,"nombreRemitente":"Gabriel","idDestinatario":1,"msj":"","fecha":"12-09-2018 01:57:04"}
{"from":1,"to":1,"nombreRemitente":"Gabriel","idDestinatario":1,"msj":"como le hago????","fecha":"12-09-2018 01:57:24"}
